{"method":"PUBLISH","prodid":"WISE TIMETABLE - MAG RIT - RAČUNALNIŠTVO IN INFORMACIJSKE TEHNOLOGIJE (BM20)","events":[{"uid":"ll-0","location":"","summary":"RAZVOJ IN UPRAVLJANJE PROGRAMSKIH SISTEMOV, G2-P4 DELTA, 2. nadstropje","description":" PR, MAG 1 RIT,  ","start":"2016-10-03T10:00:00Z","end":"2016-10-03T12:00:00Z"},{"uid":"ll-1","location":"","summary":"GENERATIVNE METODE, G2-P04, pritličje","description":" SV, MAG 1 RIT,  ","start":"2016-10-04T07:00:00Z","end":"2016-10-04T09:00:00Z"},{"uid":"ll-2","location":"","summary":"IZBRANI ALGORITMI, G2-P04, pritličje","description":" PR, MAG 1 RIT,  ","start":"2016-10-04T09:00:00Z","end":"2016-10-04T11:00:00Z"},{"uid":"ll-3","location":"","summary":"SPLETNE TEHNOLOGIJE, G2-P01, pritličje","description":" PR, MAG 1 RIT,  ","start":"2016-10-04T11:00:00Z","end":"2016-10-04T13:00:00Z"},{"uid":"ll-4","location":"","summary":"RAČUNALNIŠKA MULTIMEDIA, A-302","description":" SV, MAG 1 RIT,  ","start":"2016-10-05T08:00:00Z","end":"2016-10-05T10:00:00Z"},{"uid":"ll-5","location":"","summary":"PRINCIPI PROGRAMSKIH JEZIKOV, G2-P2 BETA, pritličje","description":" SV, MAG 1 RIT,  ","start":"2016-10-05T10:00:00Z","end":"2016-10-05T12:00:00Z"},{"uid":"ll-6","location":"","summary":"SPLETNE TEHNOLOGIJE, G2-P02, pritličje","description":" SV, MAG 1 RIT,  ","start":"2016-10-06T07:00:00Z","end":"2016-10-06T09:00:00Z"},{"uid":"ll-7","location":"","summary":"RAČUNALNIŠKA MULTIMEDIA, G2-P02, pritličje","description":" PR, MAG 1 RIT,  ","start":"2016-10-06T09:00:00Z","end":"2016-10-06T11:00:00Z"},{"uid":"ll-8","location":"","summary":"RAZVOJ IN UPRAVLJANJE PROGRAMSKIH SISTEMOV, G2-P05, pritličje","description":" SV, MAG 1 RIT,  ","start":"2016-10-06T12:00:00Z","end":"2016-10-06T14:00:00Z"},{"uid":"ll-9","location":"","summary":"GENERATIVNE METODE, A-304","description":" PR, MAG 1 RIT,  ","start":"2016-10-06T14:00:00Z","end":"2016-10-06T16:00:00Z"},{"uid":"ll-10","location":"","summary":"PRINCIPI PROGRAMSKIH JEZIKOV, A-302","description":" PR, MAG 1 RIT,  ","start":"2016-10-07T11:00:00Z","end":"2016-10-07T13:00:00Z"},{"uid":"ll-11","location":"","summary":"IZBRANI ALGORITMI, A-302","description":" SV, MAG 1 RIT,  ","start":"2016-10-07T13:00:00Z","end":"2016-10-07T15:00:00Z"},{"uid":"ll-12","location":"","summary":"IZBRANI ALGORITMI, (RU) F-201","description":" RV, MAG 1 RIT RV 2,  ","start":"2016-10-10T08:00:00Z","end":"2016-10-10T10:00:00Z"},{"uid":"ll-13","location":"","summary":"RAZVOJ IN UPRAVLJANJE PROGRAMSKIH SISTEMOV, G2-P4 DELTA, 2. nadstropje","description":" PR, MAG 1 RIT,  ","start":"2016-10-10T10:00:00Z","end":"2016-10-10T12:00:00Z"},{"uid":"ll-14","location":"","summary":"GENERATIVNE METODE, G2-P4 DELTA, 2. nadstropje","description":" PR, MAG 1 RIT,  ","start":"2016-10-10T12:00:00Z","end":"2016-10-10T14:00:00Z"},{"uid":"ll-15","location":"","summary":"GENERATIVNE METODE, (RU) G-219","description":" RV, MAG 1 RIT RV 3,  ","start":"2016-10-10T14:00:00Z","end":"2016-10-10T16:00:00Z"},{"uid":"ll-16","location":"","summary":"GENERATIVNE METODE, (RU) G-219","description":" RV, MAG 1 RIT RV 1,  ","start":"2016-10-11T07:00:00Z","end":"2016-10-11T09:00:00Z"},{"uid":"ll-17","location":"","summary":"IZBRANI ALGORITMI, G2-P04, pritličje","description":" PR, MAG 1 RIT,  ","start":"2016-10-11T09:00:00Z","end":"2016-10-11T11:00:00Z"},{"uid":"ll-18","location":"","summary":"GENERATIVNE METODE, (RU) G-219","description":" RV, MAG 1 RIT RV 2,  ","start":"2016-10-11T11:00:00Z","end":"2016-10-11T13:00:00Z"},{"uid":"ll-19","location":"","summary":"RAČUNALNIŠKA MULTIMEDIA, (RU) F-104","description":" RV, MAG 1 RIT RV 1,  ","start":"2016-10-11T11:00:00Z","end":"2016-10-11T13:00:00Z"},{"uid":"ll-20","location":"","summary":"SPLETNE TEHNOLOGIJE, (RU) C-202","description":" RV, MAG 1 RIT RV 3,  ","start":"2016-10-12T08:00:00Z","end":"2016-10-12T10:00:00Z"},{"uid":"ll-21","location":"","summary":"SPLETNE TEHNOLOGIJE, (RU) C-202","description":" RV, MAG 1 RIT RV 2,  ","start":"2016-10-12T10:00:00Z","end":"2016-10-12T12:00:00Z"},{"uid":"ll-22","location":"","summary":"PRINCIPI PROGRAMSKIH JEZIKOV, (RU) F-201","description":" RV, MAG 1 RIT RV 3,  ","start":"2016-10-12T10:00:00Z","end":"2016-10-12T12:00:00Z"},{"uid":"ll-23","location":"","summary":"RAČUNALNIŠKA MULTIMEDIA, (RU) F-104","description":" RV, MAG 1 RIT RV 3,  ","start":"2016-10-12T12:00:00Z","end":"2016-10-12T14:00:00Z"},{"uid":"ll-24","location":"","summary":"RAZVOJ IN UPRAVLJANJE PROGRAMSKIH SISTEMOV, (RU) G-219","description":" RV, MAG 1 RIT RV 3,  ","start":"2016-10-12T14:00:00Z","end":"2016-10-12T16:00:00Z"},{"uid":"ll-25","location":"","summary":"RAČUNALNIŠKA MULTIMEDIA, (RU) F-104","description":" RV, MAG 1 RIT RV 2,  ","start":"2016-10-12T14:00:00Z","end":"2016-10-12T16:00:00Z"},{"uid":"ll-26","location":"","summary":"RAZVOJ IN UPRAVLJANJE PROGRAMSKIH SISTEMOV, (RU) C-202","description":" RV, MAG 1 RIT RV 2,  ","start":"2016-10-13T07:00:00Z","end":"2016-10-13T09:00:00Z"},{"uid":"ll-27","location":"","summary":"PRINCIPI PROGRAMSKIH JEZIKOV, (RU) F-201","description":" RV, MAG 1 RIT RV 1,  ","start":"2016-10-13T07:00:00Z","end":"2016-10-13T09:00:00Z"},{"uid":"ll-28","location":"","summary":"RAČUNALNIŠKA MULTIMEDIA, G2-P02, pritličje","description":" PR, MAG 1 RIT,  ","start":"2016-10-13T09:00:00Z","end":"2016-10-13T11:00:00Z"},{"uid":"ll-29","location":"","summary":"PRINCIPI PROGRAMSKIH JEZIKOV, (RU) C-202","description":" RV, MAG 1 RIT RV 2,  ","start":"2016-10-13T11:00:00Z","end":"2016-10-13T13:00:00Z"},{"uid":"ll-30","location":"","summary":"SPLETNE TEHNOLOGIJE, G2-P01, pritličje","description":" PR, MAG 1 RIT,  ","start":"2016-10-13T15:00:00Z","end":"2016-10-13T17:00:00Z"},{"uid":"ll-31","location":"","summary":"IZBRANI ALGORITMI, (RU) F-201","description":" RV, MAG 1 RIT RV 3,  ","start":"2016-10-13T17:00:00Z","end":"2016-10-13T19:00:00Z"},{"uid":"ll-32","location":"","summary":"SPLETNE TEHNOLOGIJE, (RU) C-202","description":" RV, MAG 1 RIT RV 1,  ","start":"2016-10-13T17:00:00Z","end":"2016-10-13T19:00:00Z"},{"uid":"ll-33","location":"","summary":"RAZVOJ IN UPRAVLJANJE PROGRAMSKIH SISTEMOV, (RU) C-202","description":" RV, MAG 1 RIT RV 1,  ","start":"2016-10-14T09:00:00Z","end":"2016-10-14T11:00:00Z"},{"uid":"ll-34","location":"","summary":"PRINCIPI PROGRAMSKIH JEZIKOV, A-302","description":" PR, MAG 1 RIT,  ","start":"2016-10-14T11:00:00Z","end":"2016-10-14T13:00:00Z"},{"uid":"ll-35","location":"","summary":"IZBRANI ALGORITMI, (RU) F-201","description":" RV, MAG 1 RIT RV 1,  ","start":"2016-10-14T13:00:00Z","end":"2016-10-14T15:00:00Z"},{"uid":"ll-36","location":"","summary":"IZBRANI ALGORITMI, (RU) F-201","description":" RV, MAG 1 RIT RV 2,  ","start":"2016-10-17T08:00:00Z","end":"2016-10-17T10:00:00Z"},{"uid":"ll-37","location":"","summary":"RAZVOJ IN UPRAVLJANJE PROGRAMSKIH SISTEMOV, G2-P4 DELTA, 2. nadstropje","description":" PR, MAG 1 RIT,  ","start":"2016-10-17T10:00:00Z","end":"2016-10-17T12:00:00Z"},{"uid":"ll-38","location":"","summary":"GENERATIVNE METODE, G2-P4 DELTA, 2. nadstropje","description":" PR, MAG 1 RIT,  ","start":"2016-10-17T12:00:00Z","end":"2016-10-17T14:00:00Z"},{"uid":"ll-39","location":"","summary":"GENERATIVNE METODE, (RU) G-219","description":" RV, MAG 1 RIT RV 3,  ","start":"2016-10-17T14:00:00Z","end":"2016-10-17T16:00:00Z"},{"uid":"ll-40","location":"","summary":"GENERATIVNE METODE, (RU) G-219","description":" RV, MAG 1 RIT RV 1,  ","start":"2016-10-18T07:00:00Z","end":"2016-10-18T09:00:00Z"},{"uid":"ll-41","location":"","summary":"IZBRANI ALGORITMI, G2-P04, pritličje","description":" PR, MAG 1 RIT,  ","start":"2016-10-18T09:00:00Z","end":"2016-10-18T11:00:00Z"},{"uid":"ll-42","location":"","summary":"RAČUNALNIŠKA MULTIMEDIA, (RU) F-104","description":" RV, MAG 1 RIT RV 1,  ","start":"2016-10-18T11:00:00Z","end":"2016-10-18T13:00:00Z"},{"uid":"ll-43","location":"","summary":"GENERATIVNE METODE, (RU) G-219","description":" RV, MAG 1 RIT RV 2,  ","start":"2016-10-18T11:00:00Z","end":"2016-10-18T13:00:00Z"},{"uid":"ll-44","location":"","summary":"SPLETNE TEHNOLOGIJE, (RU) C-202","description":" RV, MAG 1 RIT RV 3,  ","start":"2016-10-19T08:00:00Z","end":"2016-10-19T10:00:00Z"},{"uid":"ll-45","location":"","summary":"SPLETNE TEHNOLOGIJE, (RU) C-202","description":" RV, MAG 1 RIT RV 2,  ","start":"2016-10-19T10:00:00Z","end":"2016-10-19T12:00:00Z"},{"uid":"ll-46","location":"","summary":"PRINCIPI PROGRAMSKIH JEZIKOV, (RU) F-201","description":" RV, MAG 1 RIT RV 3,  ","start":"2016-10-19T10:00:00Z","end":"2016-10-19T12:00:00Z"},{"uid":"ll-47","location":"","summary":"RAČUNALNIŠKA MULTIMEDIA, (RU) F-104","description":" RV, MAG 1 RIT RV 3,  ","start":"2016-10-19T12:00:00Z","end":"2016-10-19T14:00:00Z"},{"uid":"ll-48","location":"","summary":"RAZVOJ IN UPRAVLJANJE PROGRAMSKIH SISTEMOV, (RU) G-219","description":" RV, MAG 1 RIT RV 3,  ","start":"2016-10-19T14:00:00Z","end":"2016-10-19T16:00:00Z"},{"uid":"ll-49","location":"","summary":"RAČUNALNIŠKA MULTIMEDIA, (RU) F-104","description":" RV, MAG 1 RIT RV 2,  ","start":"2016-10-19T14:00:00Z","end":"2016-10-19T16:00:00Z"},{"uid":"ll-50","location":"","summary":"RAZVOJ IN UPRAVLJANJE PROGRAMSKIH SISTEMOV, (RU) C-202","description":" RV, MAG 1 RIT RV 2,  ","start":"2016-10-20T07:00:00Z","end":"2016-10-20T09:00:00Z"},{"uid":"ll-51","location":"","summary":"PRINCIPI PROGRAMSKIH JEZIKOV, (RU) F-201","description":" RV, MAG 1 RIT RV 1,  ","start":"2016-10-20T07:00:00Z","end":"2016-10-20T09:00:00Z"},{"uid":"ll-52","location":"","summary":"RAČUNALNIŠKA MULTIMEDIA, G2-P02, pritličje","description":" PR, MAG 1 RIT,  ","start":"2016-10-20T09:00:00Z","end":"2016-10-20T11:00:00Z"},{"uid":"ll-53","location":"","summary":"PRINCIPI PROGRAMSKIH JEZIKOV, (RU) C-202","description":" RV, MAG 1 RIT RV 2,  ","start":"2016-10-20T11:00:00Z","end":"2016-10-20T13:00:00Z"},{"uid":"ll-54","location":"","summary":"SPLETNE TEHNOLOGIJE, G2-P01, pritličje","description":" PR, MAG 1 RIT,  ","start":"2016-10-20T15:00:00Z","end":"2016-10-20T17:00:00Z"},{"uid":"ll-55","location":"","summary":"IZBRANI ALGORITMI, (RU) F-201","description":" RV, MAG 1 RIT RV 3,  ","start":"2016-10-20T17:00:00Z","end":"2016-10-20T19:00:00Z"},{"uid":"ll-56","location":"","summary":"SPLETNE TEHNOLOGIJE, (RU) C-202","description":" RV, MAG 1 RIT RV 1,  ","start":"2016-10-20T17:00:00Z","end":"2016-10-20T19:00:00Z"},{"uid":"ll-57","location":"","summary":"RAZVOJ IN UPRAVLJANJE PROGRAMSKIH SISTEMOV, (RU) C-202","description":" RV, MAG 1 RIT RV 1,  ","start":"2016-10-21T09:00:00Z","end":"2016-10-21T11:00:00Z"},{"uid":"ll-58","location":"","summary":"PRINCIPI PROGRAMSKIH JEZIKOV, A-302","description":" PR, MAG 1 RIT,  ","start":"2016-10-21T11:00:00Z","end":"2016-10-21T13:00:00Z"},{"uid":"ll-59","location":"","summary":"IZBRANI ALGORITMI, (RU) F-201","description":" RV, MAG 1 RIT RV 1,  ","start":"2016-10-21T13:00:00Z","end":"2016-10-21T15:00:00Z"},{"uid":"ll-60","location":"","summary":"IZBRANI ALGORITMI, (RU) F-201","description":" RV, MAG 1 RIT RV 2,  ","start":"2016-10-24T08:00:00Z","end":"2016-10-24T10:00:00Z"},{"uid":"ll-61","location":"","summary":"RAZVOJ IN UPRAVLJANJE PROGRAMSKIH SISTEMOV, G2-P4 DELTA, 2. nadstropje","description":" PR, MAG 1 RIT,  ","start":"2016-10-24T10:00:00Z","end":"2016-10-24T12:00:00Z"},{"uid":"ll-62","location":"","summary":"GENERATIVNE METODE, G2-P4 DELTA, 2. nadstropje","description":" PR, MAG 1 RIT,  ","start":"2016-10-24T12:00:00Z","end":"2016-10-24T14:00:00Z"},{"uid":"ll-63","location":"","summary":"GENERATIVNE METODE, (RU) G-219","description":" RV, MAG 1 RIT RV 3,  ","start":"2016-10-24T14:00:00Z","end":"2016-10-24T16:00:00Z"},{"uid":"ll-64","location":"","summary":"GENERATIVNE METODE, (RU) G-219","description":" RV, MAG 1 RIT RV 1,  ","start":"2016-10-25T07:00:00Z","end":"2016-10-25T09:00:00Z"},{"uid":"ll-65","location":"","summary":"IZBRANI ALGORITMI, G2-P04, pritličje","description":" PR, MAG 1 RIT,  ","start":"2016-10-25T09:00:00Z","end":"2016-10-25T11:00:00Z"},{"uid":"ll-66","location":"","summary":"RAČUNALNIŠKA MULTIMEDIA, (RU) F-104","description":" RV, MAG 1 RIT RV 1,  ","start":"2016-10-25T11:00:00Z","end":"2016-10-25T13:00:00Z"},{"uid":"ll-67","location":"","summary":"GENERATIVNE METODE, (RU) G-219","description":" RV, MAG 1 RIT RV 2,  ","start":"2016-10-25T11:00:00Z","end":"2016-10-25T13:00:00Z"},{"uid":"ll-68","location":"","summary":"SPLETNE TEHNOLOGIJE, (RU) C-202","description":" RV, MAG 1 RIT RV 3,  ","start":"2016-10-26T08:00:00Z","end":"2016-10-26T10:00:00Z"},{"uid":"ll-69","location":"","summary":"PRINCIPI PROGRAMSKIH JEZIKOV, (RU) F-201","description":" RV, MAG 1 RIT RV 3,  ","start":"2016-10-26T10:00:00Z","end":"2016-10-26T12:00:00Z"},{"uid":"ll-70","location":"","summary":"SPLETNE TEHNOLOGIJE, (RU) C-202","description":" RV, MAG 1 RIT RV 2,  ","start":"2016-10-26T10:00:00Z","end":"2016-10-26T12:00:00Z"},{"uid":"ll-71","location":"","summary":"RAČUNALNIŠKA MULTIMEDIA, (RU) F-104","description":" RV, MAG 1 RIT RV 3,  ","start":"2016-10-26T12:00:00Z","end":"2016-10-26T14:00:00Z"},{"uid":"ll-72","location":"","summary":"RAZVOJ IN UPRAVLJANJE PROGRAMSKIH SISTEMOV, (RU) G-219","description":" RV, MAG 1 RIT RV 3,  ","start":"2016-10-26T14:00:00Z","end":"2016-10-26T16:00:00Z"},{"uid":"ll-73","location":"","summary":"RAČUNALNIŠKA MULTIMEDIA, (RU) F-104","description":" RV, MAG 1 RIT RV 2,  ","start":"2016-10-26T14:00:00Z","end":"2016-10-26T16:00:00Z"},{"uid":"ll-74","location":"","summary":"RAZVOJ IN UPRAVLJANJE PROGRAMSKIH SISTEMOV, G2-P2 BETA, pritličje","description":" PR, MAG 1 RIT,  ","start":"2016-10-26T16:00:00Z","end":"2016-10-26T19:00:00Z"},{"uid":"ll-75","location":"","summary":"RAZVOJ IN UPRAVLJANJE PROGRAMSKIH SISTEMOV, (RU) C-202","description":" RV, MAG 1 RIT RV 2,  ","start":"2016-10-27T07:00:00Z","end":"2016-10-27T09:00:00Z"},{"uid":"ll-76","location":"","summary":"PRINCIPI PROGRAMSKIH JEZIKOV, (RU) F-201","description":" RV, MAG 1 RIT RV 1,  ","start":"2016-10-27T07:00:00Z","end":"2016-10-27T09:00:00Z"},{"uid":"ll-77","location":"","summary":"RAČUNALNIŠKA MULTIMEDIA, G2-P02, pritličje","description":" PR, MAG 1 RIT,  ","start":"2016-10-27T09:00:00Z","end":"2016-10-27T11:00:00Z"},{"uid":"ll-78","location":"","summary":"PRINCIPI PROGRAMSKIH JEZIKOV, (RU) C-202","description":" RV, MAG 1 RIT RV 2,  ","start":"2016-10-27T11:00:00Z","end":"2016-10-27T13:00:00Z"},{"uid":"ll-79","location":"","summary":"SPLETNE TEHNOLOGIJE, G2-P01, pritličje","description":" PR, MAG 1 RIT,  ","start":"2016-10-27T15:00:00Z","end":"2016-10-27T17:00:00Z"},{"uid":"ll-80","location":"","summary":"IZBRANI ALGORITMI, (RU) F-201","description":" RV, MAG 1 RIT RV 3,  ","start":"2016-10-27T17:00:00Z","end":"2016-10-27T19:00:00Z"},{"uid":"ll-81","location":"","summary":"SPLETNE TEHNOLOGIJE, (RU) C-202","description":" RV, MAG 1 RIT RV 1,  ","start":"2016-10-27T17:00:00Z","end":"2016-10-27T19:00:00Z"},{"uid":"ll-82","location":"","summary":"RAZVOJ IN UPRAVLJANJE PROGRAMSKIH SISTEMOV, (RU) C-202","description":" RV, MAG 1 RIT RV 1,  ","start":"2016-10-28T09:00:00Z","end":"2016-10-28T11:00:00Z"},{"uid":"ll-83","location":"","summary":"PRINCIPI PROGRAMSKIH JEZIKOV, A-302","description":" PR, MAG 1 RIT,  ","start":"2016-10-28T11:00:00Z","end":"2016-10-28T13:00:00Z"},{"uid":"ll-84","location":"","summary":"IZBRANI ALGORITMI, (RU) F-201","description":" RV, MAG 1 RIT RV 1,  ","start":"2016-10-28T13:00:00Z","end":"2016-10-28T15:00:00Z"},{"uid":"ll-85","location":"","summary":"SPLETNE TEHNOLOGIJE, (RU) C-202","description":" RV, MAG 1 RIT RV 3,  ","start":"2016-11-02T08:00:00Z","end":"2016-11-02T10:00:00Z"},{"uid":"ll-86","location":"","summary":"SPLETNE TEHNOLOGIJE, (RU) C-202","description":" RV, MAG 1 RIT RV 2,  ","start":"2016-11-02T10:00:00Z","end":"2016-11-02T12:00:00Z"},{"uid":"ll-87","location":"","summary":"PRINCIPI PROGRAMSKIH JEZIKOV, (RU) F-201","description":" RV, MAG 1 RIT RV 3,  ","start":"2016-11-02T10:00:00Z","end":"2016-11-02T12:00:00Z"},{"uid":"ll-88","location":"","summary":"RAČUNALNIŠKA MULTIMEDIA, (RU) F-104","description":" RV, MAG 1 RIT RV 3,  ","start":"2016-11-02T12:00:00Z","end":"2016-11-02T14:00:00Z"},{"uid":"ll-89","location":"","summary":"RAZVOJ IN UPRAVLJANJE PROGRAMSKIH SISTEMOV, (RU) G-219","description":" RV, MAG 1 RIT RV 3,  ","start":"2016-11-02T14:00:00Z","end":"2016-11-02T16:00:00Z"},{"uid":"ll-90","location":"","summary":"RAČUNALNIŠKA MULTIMEDIA, (RU) F-104","description":" RV, MAG 1 RIT RV 2,  ","start":"2016-11-02T14:00:00Z","end":"2016-11-02T16:00:00Z"},{"uid":"ll-91","location":"","summary":"GENERATIVNE METODE, G2-P2 BETA, pritličje","description":" PR, MAG 1 RIT,  ","start":"2016-11-02T16:00:00Z","end":"2016-11-02T18:00:00Z"},{"uid":"ll-92","location":"","summary":"IZBRANI ALGORITMI, (RU) F-201","description":" RV, MAG 1 RIT RV 2,  ","start":"2016-11-02T18:00:00Z","end":"2016-11-02T20:00:00Z"},{"uid":"ll-93","location":"","summary":"RAZVOJ IN UPRAVLJANJE PROGRAMSKIH SISTEMOV, (RU) C-202","description":" RV, MAG 1 RIT RV 2,  ","start":"2016-11-03T07:00:00Z","end":"2016-11-03T09:00:00Z"},{"uid":"ll-94","location":"","summary":"PRINCIPI PROGRAMSKIH JEZIKOV, (RU) F-201","description":" RV, MAG 1 RIT RV 1,  ","start":"2016-11-03T07:00:00Z","end":"2016-11-03T09:00:00Z"},{"uid":"ll-95","location":"","summary":"RAČUNALNIŠKA MULTIMEDIA, G2-P02, pritličje","description":" PR, MAG 1 RIT,  ","start":"2016-11-03T09:00:00Z","end":"2016-11-03T11:00:00Z"},{"uid":"ll-96","location":"","summary":"PRINCIPI PROGRAMSKIH JEZIKOV, (RU) C-202","description":" RV, MAG 1 RIT RV 2,  ","start":"2016-11-03T11:00:00Z","end":"2016-11-03T13:00:00Z"},{"uid":"ll-97","location":"","summary":"SPLETNE TEHNOLOGIJE, G2-P01, pritličje","description":" PR, MAG 1 RIT,  ","start":"2016-11-03T15:00:00Z","end":"2016-11-03T17:00:00Z"},{"uid":"ll-98","location":"","summary":"IZBRANI ALGORITMI, (RU) F-201","description":" RV, MAG 1 RIT RV 3,  ","start":"2016-11-03T17:00:00Z","end":"2016-11-03T19:00:00Z"},{"uid":"ll-99","location":"","summary":"SPLETNE TEHNOLOGIJE, (RU) C-202","description":" RV, MAG 1 RIT RV 1,  ","start":"2016-11-03T17:00:00Z","end":"2016-11-03T19:00:00Z"},{"uid":"ll-100","location":"","summary":"RAČUNALNIŠKA MULTIMEDIA, (RU) F-104","description":" RV, MAG 1 RIT RV 1,  ","start":"2016-11-04T07:00:00Z","end":"2016-11-04T09:00:00Z"},{"uid":"ll-101","location":"","summary":"RAZVOJ IN UPRAVLJANJE PROGRAMSKIH SISTEMOV, (RU) C-202","description":" RV, MAG 1 RIT RV 1,  ","start":"2016-11-04T09:00:00Z","end":"2016-11-04T11:00:00Z"},{"uid":"ll-102","location":"","summary":"PRINCIPI PROGRAMSKIH JEZIKOV, A-302","description":" PR, MAG 1 RIT,  ","start":"2016-11-04T11:00:00Z","end":"2016-11-04T13:00:00Z"},{"uid":"ll-103","location":"","summary":"IZBRANI ALGORITMI, (RU) F-201","description":" RV, MAG 1 RIT RV 1,  ","start":"2016-11-04T13:00:00Z","end":"2016-11-04T15:00:00Z"},{"uid":"ll-104","location":"","summary":"IZBRANI ALGORITMI, (RU) F-201","description":" RV, MAG 1 RIT RV 2,  ","start":"2016-11-07T08:00:00Z","end":"2016-11-07T10:00:00Z"},{"uid":"ll-105","location":"","summary":"RAZVOJ IN UPRAVLJANJE PROGRAMSKIH SISTEMOV, G2-P4 DELTA, 2. nadstropje","description":" PR, MAG 1 RIT,  ","start":"2016-11-07T10:00:00Z","end":"2016-11-07T12:00:00Z"},{"uid":"ll-106","location":"","summary":"GENERATIVNE METODE, G2-P4 DELTA, 2. nadstropje","description":" PR, MAG 1 RIT,  ","start":"2016-11-07T12:00:00Z","end":"2016-11-07T14:00:00Z"},{"uid":"ll-107","location":"","summary":"GENERATIVNE METODE, (RU) G-219","description":" RV, MAG 1 RIT RV 3,  ","start":"2016-11-07T14:00:00Z","end":"2016-11-07T16:00:00Z"},{"uid":"ll-108","location":"","summary":"GENERATIVNE METODE, (RU) G-219","description":" RV, MAG 1 RIT RV 1,  ","start":"2016-11-08T07:00:00Z","end":"2016-11-08T09:00:00Z"},{"uid":"ll-109","location":"","summary":"IZBRANI ALGORITMI, G-217,  2. nad. ","description":" PR, MAG 1 RIT,  ","start":"2016-11-08T09:00:00Z","end":"2016-11-08T11:00:00Z"},{"uid":"ll-110","location":"","summary":"GENERATIVNE METODE, (RU) G-219","description":" RV, MAG 1 RIT RV 2,  ","start":"2016-11-08T11:00:00Z","end":"2016-11-08T13:00:00Z"},{"uid":"ll-111","location":"","summary":"RAČUNALNIŠKA MULTIMEDIA, (RU) F-104","description":" RV, MAG 1 RIT RV 1,  ","start":"2016-11-08T11:00:00Z","end":"2016-11-08T13:00:00Z"},{"uid":"ll-112","location":"","summary":"GENERATIVNE METODE, (RU) G-219","description":" RV, MAG 1 RIT RV 2,  ","start":"2016-11-08T13:00:00Z","end":"2016-11-08T15:00:00Z"},{"uid":"ll-113","location":"","summary":"SPLETNE TEHNOLOGIJE, (RU) C-202","description":" RV, MAG 1 RIT RV 3,  ","start":"2016-11-09T08:00:00Z","end":"2016-11-09T10:00:00Z"},{"uid":"ll-114","location":"","summary":"SPLETNE TEHNOLOGIJE, (RU) C-202","description":" RV, MAG 1 RIT RV 2,  ","start":"2016-11-09T10:00:00Z","end":"2016-11-09T12:00:00Z"},{"uid":"ll-115","location":"","summary":"PRINCIPI PROGRAMSKIH JEZIKOV, (RU) F-201","description":" RV, MAG 1 RIT RV 3,  ","start":"2016-11-09T10:00:00Z","end":"2016-11-09T12:00:00Z"},{"uid":"ll-116","location":"","summary":"RAČUNALNIŠKA MULTIMEDIA, (RU) F-104","description":" RV, MAG 1 RIT RV 3,  ","start":"2016-11-09T12:00:00Z","end":"2016-11-09T14:00:00Z"},{"uid":"ll-117","location":"","summary":"RAZVOJ IN UPRAVLJANJE PROGRAMSKIH SISTEMOV, (RU) G-219","description":" RV, MAG 1 RIT RV 3,  ","start":"2016-11-09T14:00:00Z","end":"2016-11-09T16:00:00Z"},{"uid":"ll-118","location":"","summary":"RAČUNALNIŠKA MULTIMEDIA, (RU) F-104","description":" RV, MAG 1 RIT RV 2,  ","start":"2016-11-09T14:00:00Z","end":"2016-11-09T16:00:00Z"},{"uid":"ll-119","location":"","summary":"RAZVOJ IN UPRAVLJANJE PROGRAMSKIH SISTEMOV, (RU) C-202","description":" RV, MAG 1 RIT RV 2,  ","start":"2016-11-10T07:00:00Z","end":"2016-11-10T09:00:00Z"},{"uid":"ll-120","location":"","summary":"PRINCIPI PROGRAMSKIH JEZIKOV, (RU) F-201","description":" RV, MAG 1 RIT RV 1,  ","start":"2016-11-10T07:00:00Z","end":"2016-11-10T09:00:00Z"},{"uid":"ll-121","location":"","summary":"RAČUNALNIŠKA MULTIMEDIA, G2-P02, pritličje","description":" PR, MAG 1 RIT,  ","start":"2016-11-10T09:00:00Z","end":"2016-11-10T11:00:00Z"},{"uid":"ll-122","location":"","summary":"PRINCIPI PROGRAMSKIH JEZIKOV, (RU) C-202","description":" RV, MAG 1 RIT RV 2,  ","start":"2016-11-10T11:00:00Z","end":"2016-11-10T13:00:00Z"},{"uid":"ll-123","location":"","summary":"SPLETNE TEHNOLOGIJE, G2-P01, pritličje","description":" PR, MAG 1 RIT,  ","start":"2016-11-10T15:00:00Z","end":"2016-11-10T17:00:00Z"},{"uid":"ll-124","location":"","summary":"IZBRANI ALGORITMI, (RU) F-201","description":" RV, MAG 1 RIT RV 3,  ","start":"2016-11-10T17:00:00Z","end":"2016-11-10T19:00:00Z"},{"uid":"ll-125","location":"","summary":"SPLETNE TEHNOLOGIJE, (RU) C-202","description":" RV, MAG 1 RIT RV 1,  ","start":"2016-11-10T17:00:00Z","end":"2016-11-10T19:00:00Z"},{"uid":"ll-126","location":"","summary":"RAZVOJ IN UPRAVLJANJE PROGRAMSKIH SISTEMOV, (RU) C-202","description":" RV, MAG 1 RIT RV 1,  ","start":"2016-11-11T09:00:00Z","end":"2016-11-11T11:00:00Z"},{"uid":"ll-127","location":"","summary":"PRINCIPI PROGRAMSKIH JEZIKOV, A-302","description":" PR, MAG 1 RIT,  ","start":"2016-11-11T11:00:00Z","end":"2016-11-11T13:00:00Z"},{"uid":"ll-128","location":"","summary":"IZBRANI ALGORITMI, (RU) F-201","description":" RV, MAG 1 RIT RV 1,  ","start":"2016-11-11T13:00:00Z","end":"2016-11-11T15:00:00Z"},{"uid":"ll-129","location":"","summary":"IZBRANI ALGORITMI, (RU) F-201","description":" RV, MAG 1 RIT RV 2,  ","start":"2016-11-14T08:00:00Z","end":"2016-11-14T10:00:00Z"},{"uid":"ll-130","location":"","summary":"RAZVOJ IN UPRAVLJANJE PROGRAMSKIH SISTEMOV, G2-P4 DELTA, 2. nadstropje","description":" PR, MAG 1 RIT,  ","start":"2016-11-14T10:00:00Z","end":"2016-11-14T12:00:00Z"},{"uid":"ll-131","location":"","summary":"GENERATIVNE METODE, G2-P4 DELTA, 2. nadstropje","description":" PR, MAG 1 RIT,  ","start":"2016-11-14T12:00:00Z","end":"2016-11-14T14:00:00Z"},{"uid":"ll-132","location":"","summary":"GENERATIVNE METODE, (RU) G-219","description":" RV, MAG 1 RIT RV 3,  ","start":"2016-11-14T14:00:00Z","end":"2016-11-14T16:00:00Z"},{"uid":"ll-133","location":"","summary":"GENERATIVNE METODE, (RU) G-219","description":" RV, MAG 1 RIT RV 1,  ","start":"2016-11-15T07:00:00Z","end":"2016-11-15T09:00:00Z"},{"uid":"ll-134","location":"","summary":"IZBRANI ALGORITMI, G2-P04, pritličje","description":" PR, MAG 1 RIT,  ","start":"2016-11-15T09:00:00Z","end":"2016-11-15T11:00:00Z"},{"uid":"ll-135","location":"","summary":"GENERATIVNE METODE, (RU) G-219","description":" RV, MAG 1 RIT RV 2,  ","start":"2016-11-15T11:00:00Z","end":"2016-11-15T13:00:00Z"},{"uid":"ll-136","location":"","summary":"RAČUNALNIŠKA MULTIMEDIA, (RU) F-104","description":" RV, MAG 1 RIT RV 1,  ","start":"2016-11-15T11:00:00Z","end":"2016-11-15T13:00:00Z"},{"uid":"ll-137","location":"","summary":"GENERATIVNE METODE, (RU) G-219","description":" RV, MAG 1 RIT RV 3,  ","start":"2016-11-15T13:00:00Z","end":"2016-11-15T15:00:00Z"},{"uid":"ll-138","location":"","summary":"SPLETNE TEHNOLOGIJE, (RU) C-202","description":" RV, MAG 1 RIT RV 3,  ","start":"2016-11-16T08:00:00Z","end":"2016-11-16T10:00:00Z"},{"uid":"ll-139","location":"","summary":"SPLETNE TEHNOLOGIJE, (RU) C-202","description":" RV, MAG 1 RIT RV 2,  ","start":"2016-11-16T10:00:00Z","end":"2016-11-16T12:00:00Z"},{"uid":"ll-140","location":"","summary":"PRINCIPI PROGRAMSKIH JEZIKOV, (RU) F-201","description":" RV, MAG 1 RIT RV 3,  ","start":"2016-11-16T10:00:00Z","end":"2016-11-16T12:00:00Z"},{"uid":"ll-141","location":"","summary":"RAČUNALNIŠKA MULTIMEDIA, (RU) F-104","description":" RV, MAG 1 RIT RV 3,  ","start":"2016-11-16T12:00:00Z","end":"2016-11-16T14:00:00Z"},{"uid":"ll-142","location":"","summary":"RAČUNALNIŠKA MULTIMEDIA, (RU) F-104","description":" RV, MAG 1 RIT RV 2,  ","start":"2016-11-16T14:00:00Z","end":"2016-11-16T16:00:00Z"},{"uid":"ll-143","location":"","summary":"RAZVOJ IN UPRAVLJANJE PROGRAMSKIH SISTEMOV, (RU) G-219","description":" RV, MAG 1 RIT RV 3,  ","start":"2016-11-16T14:00:00Z","end":"2016-11-16T16:00:00Z"},{"uid":"ll-144","location":"","summary":"IZBRANI ALGORITMI, G2-P2 BETA, pritličje","description":" PR, MAG 1 RIT,  ","start":"2016-11-16T16:00:00Z","end":"2016-11-16T18:00:00Z"},{"uid":"ll-145","location":"","summary":"RAZVOJ IN UPRAVLJANJE PROGRAMSKIH SISTEMOV, (RU) C-202","description":" RV, MAG 1 RIT RV 2,  ","start":"2016-11-17T07:00:00Z","end":"2016-11-17T09:00:00Z"},{"uid":"ll-146","location":"","summary":"PRINCIPI PROGRAMSKIH JEZIKOV, (RU) F-201","description":" RV, MAG 1 RIT RV 1,  ","start":"2016-11-17T07:00:00Z","end":"2016-11-17T09:00:00Z"},{"uid":"ll-147","location":"","summary":"RAČUNALNIŠKA MULTIMEDIA, G2-P02, pritličje","description":" PR, MAG 1 RIT,  ","start":"2016-11-17T09:00:00Z","end":"2016-11-17T11:00:00Z"},{"uid":"ll-148","location":"","summary":"PRINCIPI PROGRAMSKIH JEZIKOV, (RU) C-202","description":" RV, MAG 1 RIT RV 2,  ","start":"2016-11-17T11:00:00Z","end":"2016-11-17T13:00:00Z"},{"uid":"ll-149","location":"","summary":"SPLETNE TEHNOLOGIJE, G2-P01, pritličje","description":" PR, MAG 1 RIT,  ","start":"2016-11-17T15:00:00Z","end":"2016-11-17T17:00:00Z"},{"uid":"ll-150","location":"","summary":"IZBRANI ALGORITMI, (RU) F-201","description":" RV, MAG 1 RIT RV 3,  ","start":"2016-11-17T17:00:00Z","end":"2016-11-17T19:00:00Z"},{"uid":"ll-151","location":"","summary":"SPLETNE TEHNOLOGIJE, (RU) C-202","description":" RV, MAG 1 RIT RV 1,  ","start":"2016-11-17T17:00:00Z","end":"2016-11-17T19:00:00Z"},{"uid":"ll-152","location":"","summary":"RAZVOJ IN UPRAVLJANJE PROGRAMSKIH SISTEMOV, (RU) C-202","description":" RV, MAG 1 RIT RV 1,  ","start":"2016-11-18T09:00:00Z","end":"2016-11-18T11:00:00Z"},{"uid":"ll-153","location":"","summary":"PRINCIPI PROGRAMSKIH JEZIKOV, A-302","description":" PR, MAG 1 RIT,  ","start":"2016-11-18T11:00:00Z","end":"2016-11-18T13:00:00Z"},{"uid":"ll-154","location":"","summary":"IZBRANI ALGORITMI, (RU) F-201","description":" RV, MAG 1 RIT RV 1,  ","start":"2016-11-18T13:00:00Z","end":"2016-11-18T15:00:00Z"},{"uid":"ll-155","location":"","summary":"IZBRANI ALGORITMI, (RU) F-201","description":" RV, MAG 1 RIT RV 2,  ","start":"2016-11-21T08:00:00Z","end":"2016-11-21T10:00:00Z"},{"uid":"ll-156","location":"","summary":"RAZVOJ IN UPRAVLJANJE PROGRAMSKIH SISTEMOV, G2-P4 DELTA, 2. nadstropje","description":" PR, MAG 1 RIT,  ","start":"2016-11-21T10:00:00Z","end":"2016-11-21T12:00:00Z"},{"uid":"ll-157","location":"","summary":"GENERATIVNE METODE, G2-P4 DELTA, 2. nadstropje","description":" PR, MAG 1 RIT,  ","start":"2016-11-21T12:00:00Z","end":"2016-11-21T14:00:00Z"},{"uid":"ll-158","location":"","summary":"GENERATIVNE METODE, (RU) G-219","description":" RV, MAG 1 RIT RV 3,  ","start":"2016-11-21T14:00:00Z","end":"2016-11-21T16:00:00Z"},{"uid":"ll-159","location":"","summary":"GENERATIVNE METODE, (RU) G-219","description":" RV, MAG 1 RIT RV 1,  ","start":"2016-11-22T07:00:00Z","end":"2016-11-22T09:00:00Z"},{"uid":"ll-160","location":"","summary":"IZBRANI ALGORITMI, G2-P04, pritličje","description":" PR, MAG 1 RIT,  ","start":"2016-11-22T09:00:00Z","end":"2016-11-22T11:00:00Z"},{"uid":"ll-161","location":"","summary":"GENERATIVNE METODE, (RU) G-219","description":" RV, MAG 1 RIT RV 2,  ","start":"2016-11-22T11:00:00Z","end":"2016-11-22T13:00:00Z"},{"uid":"ll-162","location":"","summary":"RAČUNALNIŠKA MULTIMEDIA, (RU) F-104","description":" RV, MAG 1 RIT RV 1,  ","start":"2016-11-22T11:00:00Z","end":"2016-11-22T13:00:00Z"},{"uid":"ll-163","location":"","summary":"GENERATIVNE METODE, (RU) G-219","description":" RV, MAG 1 RIT RV 1,  ","start":"2016-11-22T13:00:00Z","end":"2016-11-22T15:00:00Z"},{"uid":"ll-164","location":"","summary":"SPLETNE TEHNOLOGIJE, (RU) C-202","description":" RV, MAG 1 RIT RV 3,  ","start":"2016-11-23T08:00:00Z","end":"2016-11-23T10:00:00Z"},{"uid":"ll-165","location":"","summary":"SPLETNE TEHNOLOGIJE, (RU) C-202","description":" RV, MAG 1 RIT RV 2,  ","start":"2016-11-23T10:00:00Z","end":"2016-11-23T12:00:00Z"},{"uid":"ll-166","location":"","summary":"PRINCIPI PROGRAMSKIH JEZIKOV, (RU) F-201","description":" RV, MAG 1 RIT RV 3,  ","start":"2016-11-23T10:00:00Z","end":"2016-11-23T12:00:00Z"},{"uid":"ll-167","location":"","summary":"RAČUNALNIŠKA MULTIMEDIA, (RU) F-104","description":" RV, MAG 1 RIT RV 3,  ","start":"2016-11-23T12:00:00Z","end":"2016-11-23T14:00:00Z"},{"uid":"ll-168","location":"","summary":"RAZVOJ IN UPRAVLJANJE PROGRAMSKIH SISTEMOV, (RU) G-219","description":" RV, MAG 1 RIT RV 3,  ","start":"2016-11-23T14:00:00Z","end":"2016-11-23T16:00:00Z"},{"uid":"ll-169","location":"","summary":"RAČUNALNIŠKA MULTIMEDIA, (RU) F-104","description":" RV, MAG 1 RIT RV 2,  ","start":"2016-11-23T14:00:00Z","end":"2016-11-23T16:00:00Z"},{"uid":"ll-170","location":"","summary":"RAZVOJ IN UPRAVLJANJE PROGRAMSKIH SISTEMOV, (RU) C-202","description":" RV, MAG 1 RIT RV 2,  ","start":"2016-11-24T07:00:00Z","end":"2016-11-24T09:00:00Z"},{"uid":"ll-171","location":"","summary":"PRINCIPI PROGRAMSKIH JEZIKOV, (RU) F-201","description":" RV, MAG 1 RIT RV 1,  ","start":"2016-11-24T07:00:00Z","end":"2016-11-24T09:00:00Z"},{"uid":"ll-172","location":"","summary":"RAČUNALNIŠKA MULTIMEDIA, G2-P02, pritličje","description":" PR, MAG 1 RIT,  ","start":"2016-11-24T09:00:00Z","end":"2016-11-24T11:00:00Z"},{"uid":"ll-173","location":"","summary":"PRINCIPI PROGRAMSKIH JEZIKOV, (RU) C-202","description":" RV, MAG 1 RIT RV 2,  ","start":"2016-11-24T11:00:00Z","end":"2016-11-24T13:00:00Z"},{"uid":"ll-174","location":"","summary":"SPLETNE TEHNOLOGIJE, G2-P01, pritličje","description":" PR, MAG 1 RIT,  ","start":"2016-11-24T15:00:00Z","end":"2016-11-24T17:00:00Z"},{"uid":"ll-175","location":"","summary":"IZBRANI ALGORITMI, (RU) F-201","description":" RV, MAG 1 RIT RV 3,  ","start":"2016-11-24T17:00:00Z","end":"2016-11-24T19:00:00Z"},{"uid":"ll-176","location":"","summary":"SPLETNE TEHNOLOGIJE, (RU) C-202","description":" RV, MAG 1 RIT RV 1,  ","start":"2016-11-24T17:00:00Z","end":"2016-11-24T19:00:00Z"},{"uid":"ll-177","location":"","summary":"RAZVOJ IN UPRAVLJANJE PROGRAMSKIH SISTEMOV, (RU) C-202","description":" RV, MAG 1 RIT RV 1,  ","start":"2016-11-25T09:00:00Z","end":"2016-11-25T11:00:00Z"},{"uid":"ll-178","location":"","summary":"PRINCIPI PROGRAMSKIH JEZIKOV, A-302","description":" PR, MAG 1 RIT,  ","start":"2016-11-25T11:00:00Z","end":"2016-11-25T13:00:00Z"},{"uid":"ll-179","location":"","summary":"IZBRANI ALGORITMI, (RU) F-201","description":" RV, MAG 1 RIT RV 1,  ","start":"2016-11-25T13:00:00Z","end":"2016-11-25T15:00:00Z"},{"uid":"ll-180","location":"","summary":"IZBRANI ALGORITMI, (RU) F-201","description":" RV, MAG 1 RIT RV 2,  ","start":"2016-11-28T08:00:00Z","end":"2016-11-28T10:00:00Z"},{"uid":"ll-181","location":"","summary":"RAZVOJ IN UPRAVLJANJE PROGRAMSKIH SISTEMOV, G2-P4 DELTA, 2. nadstropje","description":" PR, MAG 1 RIT,  ","start":"2016-11-28T10:00:00Z","end":"2016-11-28T12:00:00Z"},{"uid":"ll-182","location":"","summary":"GENERATIVNE METODE, G2-P4 DELTA, 2. nadstropje","description":" PR, MAG 1 RIT,  ","start":"2016-11-28T12:00:00Z","end":"2016-11-28T14:00:00Z"},{"uid":"ll-183","location":"","summary":"GENERATIVNE METODE, (RU) G-219","description":" RV, MAG 1 RIT RV 3,  ","start":"2016-11-28T14:00:00Z","end":"2016-11-28T16:00:00Z"},{"uid":"ll-184","location":"","summary":"GENERATIVNE METODE, (RU) G-219","description":" RV, MAG 1 RIT RV 1,  ","start":"2016-11-29T07:00:00Z","end":"2016-11-29T09:00:00Z"},{"uid":"ll-185","location":"","summary":"IZBRANI ALGORITMI, G2-P04, pritličje","description":" PR, MAG 1 RIT,  ","start":"2016-11-29T09:00:00Z","end":"2016-11-29T11:00:00Z"},{"uid":"ll-186","location":"","summary":"RAČUNALNIŠKA MULTIMEDIA, (RU) F-104","description":" RV, MAG 1 RIT RV 1,  ","start":"2016-11-29T11:00:00Z","end":"2016-11-29T13:00:00Z"},{"uid":"ll-187","location":"","summary":"GENERATIVNE METODE, (RU) G-219","description":" RV, MAG 1 RIT RV 2,  ","start":"2016-11-29T11:00:00Z","end":"2016-11-29T13:00:00Z"},{"uid":"ll-188","location":"","summary":"SPLETNE TEHNOLOGIJE, (RU) C-202","description":" RV, MAG 1 RIT RV 3,  ","start":"2016-11-30T08:00:00Z","end":"2016-11-30T10:00:00Z"},{"uid":"ll-189","location":"","summary":"SPLETNE TEHNOLOGIJE, (RU) C-202","description":" RV, MAG 1 RIT RV 2,  ","start":"2016-11-30T10:00:00Z","end":"2016-11-30T12:00:00Z"},{"uid":"ll-190","location":"","summary":"PRINCIPI PROGRAMSKIH JEZIKOV, (RU) F-201","description":" RV, MAG 1 RIT RV 3,  ","start":"2016-11-30T10:00:00Z","end":"2016-11-30T12:00:00Z"},{"uid":"ll-191","location":"","summary":"RAČUNALNIŠKA MULTIMEDIA, (RU) F-104","description":" RV, MAG 1 RIT RV 3,  ","start":"2016-11-30T12:00:00Z","end":"2016-11-30T14:00:00Z"},{"uid":"ll-192","location":"","summary":"RAZVOJ IN UPRAVLJANJE PROGRAMSKIH SISTEMOV, (RU) G-219","description":" RV, MAG 1 RIT RV 3,  ","start":"2016-11-30T14:00:00Z","end":"2016-11-30T16:00:00Z"},{"uid":"ll-193","location":"","summary":"RAČUNALNIŠKA MULTIMEDIA, (RU) F-104","description":" RV, MAG 1 RIT RV 2,  ","start":"2016-11-30T14:00:00Z","end":"2016-11-30T16:00:00Z"},{"uid":"ll-194","location":"","summary":"RAZVOJ IN UPRAVLJANJE PROGRAMSKIH SISTEMOV, (RU) C-202","description":" RV, MAG 1 RIT RV 2,  ","start":"2016-12-01T07:00:00Z","end":"2016-12-01T09:00:00Z"},{"uid":"ll-195","location":"","summary":"PRINCIPI PROGRAMSKIH JEZIKOV, (RU) F-201","description":" RV, MAG 1 RIT RV 1,  ","start":"2016-12-01T07:00:00Z","end":"2016-12-01T09:00:00Z"},{"uid":"ll-196","location":"","summary":"RAČUNALNIŠKA MULTIMEDIA, G2-P02, pritličje","description":" PR, MAG 1 RIT,  ","start":"2016-12-01T09:00:00Z","end":"2016-12-01T11:00:00Z"},{"uid":"ll-197","location":"","summary":"PRINCIPI PROGRAMSKIH JEZIKOV, (RU) C-202","description":" RV, MAG 1 RIT RV 2,  ","start":"2016-12-01T11:00:00Z","end":"2016-12-01T13:00:00Z"},{"uid":"ll-198","location":"","summary":"SPLETNE TEHNOLOGIJE, G2-P01, pritličje","description":" PR, MAG 1 RIT,  ","start":"2016-12-01T15:00:00Z","end":"2016-12-01T17:00:00Z"},{"uid":"ll-199","location":"","summary":"SPLETNE TEHNOLOGIJE, (RU) C-202","description":" RV, MAG 1 RIT RV 1,  ","start":"2016-12-01T17:00:00Z","end":"2016-12-01T19:00:00Z"},{"uid":"ll-200","location":"","summary":"IZBRANI ALGORITMI, (RU) F-201","description":" RV, MAG 1 RIT RV 3,  ","start":"2016-12-01T17:00:00Z","end":"2016-12-01T19:00:00Z"},{"uid":"ll-201","location":"","summary":"RAZVOJ IN UPRAVLJANJE PROGRAMSKIH SISTEMOV, (RU) C-202","description":" RV, MAG 1 RIT RV 1,  ","start":"2016-12-02T09:00:00Z","end":"2016-12-02T11:00:00Z"},{"uid":"ll-202","location":"","summary":"PRINCIPI PROGRAMSKIH JEZIKOV, A-302","description":" PR, MAG 1 RIT,  ","start":"2016-12-02T11:00:00Z","end":"2016-12-02T13:00:00Z"},{"uid":"ll-203","location":"","summary":"IZBRANI ALGORITMI, (RU) F-201","description":" RV, MAG 1 RIT RV 1,  ","start":"2016-12-02T13:00:00Z","end":"2016-12-02T15:00:00Z"},{"uid":"ll-204","location":"","summary":"IZBRANI ALGORITMI, (RU) F-201","description":" RV, MAG 1 RIT RV 2,  ","start":"2016-12-05T08:00:00Z","end":"2016-12-05T10:00:00Z"},{"uid":"ll-205","location":"","summary":"RAZVOJ IN UPRAVLJANJE PROGRAMSKIH SISTEMOV, G2-P4 DELTA, 2. nadstropje","description":" PR, MAG 1 RIT,  ","start":"2016-12-05T10:00:00Z","end":"2016-12-05T12:00:00Z"},{"uid":"ll-206","location":"","summary":"GENERATIVNE METODE, G2-P4 DELTA, 2. nadstropje","description":" PR, MAG 1 RIT,  ","start":"2016-12-05T12:00:00Z","end":"2016-12-05T14:00:00Z"},{"uid":"ll-207","location":"","summary":"GENERATIVNE METODE, (RU) G-219","description":" RV, MAG 1 RIT RV 3,  ","start":"2016-12-05T14:00:00Z","end":"2016-12-05T16:00:00Z"},{"uid":"ll-208","location":"","summary":"GENERATIVNE METODE, (RU) G-219","description":" RV, MAG 1 RIT RV 1,  ","start":"2016-12-06T07:00:00Z","end":"2016-12-06T09:00:00Z"},{"uid":"ll-209","location":"","summary":"IZBRANI ALGORITMI, G2-P04, pritličje","description":" PR, MAG 1 RIT,  ","start":"2016-12-06T09:00:00Z","end":"2016-12-06T11:00:00Z"},{"uid":"ll-210","location":"","summary":"RAČUNALNIŠKA MULTIMEDIA, (RU) F-104","description":" RV, MAG 1 RIT RV 1,  ","start":"2016-12-06T11:00:00Z","end":"2016-12-06T13:00:00Z"},{"uid":"ll-211","location":"","summary":"GENERATIVNE METODE, (RU) G-219","description":" RV, MAG 1 RIT RV 2,  ","start":"2016-12-06T11:00:00Z","end":"2016-12-06T13:00:00Z"},{"uid":"ll-212","location":"","summary":"SPLETNE TEHNOLOGIJE, (RU) C-202","description":" RV, MAG 1 RIT RV 3,  ","start":"2016-12-07T08:00:00Z","end":"2016-12-07T10:00:00Z"},{"uid":"ll-213","location":"","summary":"SPLETNE TEHNOLOGIJE, (RU) C-202","description":" RV, MAG 1 RIT RV 2,  ","start":"2016-12-07T10:00:00Z","end":"2016-12-07T12:00:00Z"},{"uid":"ll-214","location":"","summary":"PRINCIPI PROGRAMSKIH JEZIKOV, (RU) F-201","description":" RV, MAG 1 RIT RV 3,  ","start":"2016-12-07T10:00:00Z","end":"2016-12-07T12:00:00Z"},{"uid":"ll-215","location":"","summary":"RAČUNALNIŠKA MULTIMEDIA, (RU) F-104","description":" RV, MAG 1 RIT RV 3,  ","start":"2016-12-07T12:00:00Z","end":"2016-12-07T14:00:00Z"},{"uid":"ll-216","location":"","summary":"RAZVOJ IN UPRAVLJANJE PROGRAMSKIH SISTEMOV, (RU) G-219","description":" RV, MAG 1 RIT RV 3,  ","start":"2016-12-07T14:00:00Z","end":"2016-12-07T16:00:00Z"},{"uid":"ll-217","location":"","summary":"RAČUNALNIŠKA MULTIMEDIA, (RU) F-104","description":" RV, MAG 1 RIT RV 2,  ","start":"2016-12-07T14:00:00Z","end":"2016-12-07T16:00:00Z"},{"uid":"ll-218","location":"","summary":"RAZVOJ IN UPRAVLJANJE PROGRAMSKIH SISTEMOV, (RU) C-202","description":" RV, MAG 1 RIT RV 2,  ","start":"2016-12-08T07:00:00Z","end":"2016-12-08T09:00:00Z"},{"uid":"ll-219","location":"","summary":"PRINCIPI PROGRAMSKIH JEZIKOV, (RU) F-201","description":" RV, MAG 1 RIT RV 1,  ","start":"2016-12-08T07:00:00Z","end":"2016-12-08T09:00:00Z"},{"uid":"ll-220","location":"","summary":"RAČUNALNIŠKA MULTIMEDIA, G2-P02, pritličje","description":" PR, MAG 1 RIT,  ","start":"2016-12-08T09:00:00Z","end":"2016-12-08T11:00:00Z"},{"uid":"ll-221","location":"","summary":"PRINCIPI PROGRAMSKIH JEZIKOV, (RU) C-202","description":" RV, MAG 1 RIT RV 2,  ","start":"2016-12-08T11:00:00Z","end":"2016-12-08T13:00:00Z"},{"uid":"ll-222","location":"","summary":"SPLETNE TEHNOLOGIJE, G2-P01, pritličje","description":" PR, MAG 1 RIT,  ","start":"2016-12-08T15:00:00Z","end":"2016-12-08T17:00:00Z"},{"uid":"ll-223","location":"","summary":"IZBRANI ALGORITMI, (RU) F-201","description":" RV, MAG 1 RIT RV 3,  ","start":"2016-12-08T17:00:00Z","end":"2016-12-08T19:00:00Z"},{"uid":"ll-224","location":"","summary":"SPLETNE TEHNOLOGIJE, (RU) C-202","description":" RV, MAG 1 RIT RV 1,  ","start":"2016-12-08T17:00:00Z","end":"2016-12-08T19:00:00Z"},{"uid":"ll-225","location":"","summary":"RAZVOJ IN UPRAVLJANJE PROGRAMSKIH SISTEMOV, (RU) C-202","description":" RV, MAG 1 RIT RV 1,  ","start":"2016-12-09T09:00:00Z","end":"2016-12-09T11:00:00Z"},{"uid":"ll-226","location":"","summary":"PRINCIPI PROGRAMSKIH JEZIKOV, A-302","description":" PR, MAG 1 RIT,  ","start":"2016-12-09T11:00:00Z","end":"2016-12-09T13:00:00Z"},{"uid":"ll-227","location":"","summary":"IZBRANI ALGORITMI, (RU) F-201","description":" RV, MAG 1 RIT RV 1,  ","start":"2016-12-09T13:00:00Z","end":"2016-12-09T15:00:00Z"},{"uid":"ll-228","location":"","summary":"IZBRANI ALGORITMI, (RU) F-201","description":" RV, MAG 1 RIT RV 2,  ","start":"2016-12-12T08:00:00Z","end":"2016-12-12T10:00:00Z"},{"uid":"ll-229","location":"","summary":"RAZVOJ IN UPRAVLJANJE PROGRAMSKIH SISTEMOV, G2-P4 DELTA, 2. nadstropje","description":" PR, MAG 1 RIT,  ","start":"2016-12-12T10:00:00Z","end":"2016-12-12T12:00:00Z"},{"uid":"ll-230","location":"","summary":"GENERATIVNE METODE, G2-P4 DELTA, 2. nadstropje","description":" PR, MAG 1 RIT,  ","start":"2016-12-12T12:00:00Z","end":"2016-12-12T14:00:00Z"},{"uid":"ll-231","location":"","summary":"GENERATIVNE METODE, (RU) G-219","description":" RV, MAG 1 RIT RV 3,  ","start":"2016-12-12T14:00:00Z","end":"2016-12-12T16:00:00Z"},{"uid":"ll-232","location":"","summary":"GENERATIVNE METODE, (RU) G-219","description":" RV, MAG 1 RIT RV 1,  ","start":"2016-12-13T07:00:00Z","end":"2016-12-13T09:00:00Z"},{"uid":"ll-233","location":"","summary":"IZBRANI ALGORITMI, G2-P04, pritličje","description":" PR, MAG 1 RIT,  ","start":"2016-12-13T09:00:00Z","end":"2016-12-13T11:00:00Z"},{"uid":"ll-234","location":"","summary":"RAČUNALNIŠKA MULTIMEDIA, (RU) F-104","description":" RV, MAG 1 RIT RV 1,  ","start":"2016-12-13T11:00:00Z","end":"2016-12-13T13:00:00Z"},{"uid":"ll-235","location":"","summary":"GENERATIVNE METODE, (RU) G-219","description":" RV, MAG 1 RIT RV 2,  ","start":"2016-12-13T11:00:00Z","end":"2016-12-13T13:00:00Z"},{"uid":"ll-236","location":"","summary":"SPLETNE TEHNOLOGIJE, (RU) C-202","description":" RV, MAG 1 RIT RV 3,  ","start":"2016-12-14T08:00:00Z","end":"2016-12-14T10:00:00Z"},{"uid":"ll-237","location":"","summary":"SPLETNE TEHNOLOGIJE, (RU) C-202","description":" RV, MAG 1 RIT RV 2,  ","start":"2016-12-14T10:00:00Z","end":"2016-12-14T12:00:00Z"},{"uid":"ll-238","location":"","summary":"PRINCIPI PROGRAMSKIH JEZIKOV, (RU) F-201","description":" RV, MAG 1 RIT RV 3,  ","start":"2016-12-14T10:00:00Z","end":"2016-12-14T12:00:00Z"},{"uid":"ll-239","location":"","summary":"RAČUNALNIŠKA MULTIMEDIA, (RU) F-104","description":" RV, MAG 1 RIT RV 3,  ","start":"2016-12-14T12:00:00Z","end":"2016-12-14T14:00:00Z"},{"uid":"ll-240","location":"","summary":"RAZVOJ IN UPRAVLJANJE PROGRAMSKIH SISTEMOV, (RU) G-219","description":" RV, MAG 1 RIT RV 3,  ","start":"2016-12-14T14:00:00Z","end":"2016-12-14T16:00:00Z"},{"uid":"ll-241","location":"","summary":"RAČUNALNIŠKA MULTIMEDIA, (RU) F-104","description":" RV, MAG 1 RIT RV 2,  ","start":"2016-12-14T14:00:00Z","end":"2016-12-14T16:00:00Z"},{"uid":"ll-242","location":"","summary":"RAZVOJ IN UPRAVLJANJE PROGRAMSKIH SISTEMOV, (RU) C-202","description":" RV, MAG 1 RIT RV 2,  ","start":"2016-12-15T07:00:00Z","end":"2016-12-15T09:00:00Z"},{"uid":"ll-243","location":"","summary":"PRINCIPI PROGRAMSKIH JEZIKOV, (RU) F-201","description":" RV, MAG 1 RIT RV 1,  ","start":"2016-12-15T07:00:00Z","end":"2016-12-15T09:00:00Z"},{"uid":"ll-244","location":"","summary":"RAČUNALNIŠKA MULTIMEDIA, G2-P02, pritličje","description":" PR, MAG 1 RIT,  ","start":"2016-12-15T09:00:00Z","end":"2016-12-15T11:00:00Z"},{"uid":"ll-245","location":"","summary":"PRINCIPI PROGRAMSKIH JEZIKOV, (RU) C-202","description":" RV, MAG 1 RIT RV 2,  ","start":"2016-12-15T11:00:00Z","end":"2016-12-15T13:00:00Z"},{"uid":"ll-246","location":"","summary":"SPLETNE TEHNOLOGIJE, G2-P01, pritličje","description":" PR, MAG 1 RIT,  ","start":"2016-12-15T15:00:00Z","end":"2016-12-15T17:00:00Z"},{"uid":"ll-247","location":"","summary":"IZBRANI ALGORITMI, (RU) F-201","description":" RV, MAG 1 RIT RV 3,  ","start":"2016-12-15T17:00:00Z","end":"2016-12-15T19:00:00Z"},{"uid":"ll-248","location":"","summary":"SPLETNE TEHNOLOGIJE, (RU) C-202","description":" RV, MAG 1 RIT RV 1,  ","start":"2016-12-15T17:00:00Z","end":"2016-12-15T19:00:00Z"},{"uid":"ll-249","location":"","summary":"RAZVOJ IN UPRAVLJANJE PROGRAMSKIH SISTEMOV, (RU) C-202","description":" RV, MAG 1 RIT RV 1,  ","start":"2016-12-16T09:00:00Z","end":"2016-12-16T11:00:00Z"},{"uid":"ll-250","location":"","summary":"PRINCIPI PROGRAMSKIH JEZIKOV, A-302","description":" PR, MAG 1 RIT,  ","start":"2016-12-16T11:00:00Z","end":"2016-12-16T13:00:00Z"},{"uid":"ll-251","location":"","summary":"IZBRANI ALGORITMI, (RU) F-201","description":" RV, MAG 1 RIT RV 1,  ","start":"2016-12-16T13:00:00Z","end":"2016-12-16T15:00:00Z"},{"uid":"ll-252","location":"","summary":"IZBRANI ALGORITMI, (RU) F-201","description":" RV, MAG 1 RIT RV 2,  ","start":"2016-12-19T08:00:00Z","end":"2016-12-19T10:00:00Z"},{"uid":"ll-253","location":"","summary":"RAZVOJ IN UPRAVLJANJE PROGRAMSKIH SISTEMOV, G2-P4 DELTA, 2. nadstropje","description":" PR, MAG 1 RIT,  ","start":"2016-12-19T10:00:00Z","end":"2016-12-19T12:00:00Z"},{"uid":"ll-254","location":"","summary":"GENERATIVNE METODE, G2-P4 DELTA, 2. nadstropje","description":" PR, MAG 1 RIT,  ","start":"2016-12-19T12:00:00Z","end":"2016-12-19T14:00:00Z"},{"uid":"ll-255","location":"","summary":"GENERATIVNE METODE, (RU) G-219","description":" RV, MAG 1 RIT RV 3,  ","start":"2016-12-19T14:00:00Z","end":"2016-12-19T16:00:00Z"},{"uid":"ll-256","location":"","summary":"GENERATIVNE METODE, (RU) G-219","description":" RV, MAG 1 RIT RV 1,  ","start":"2016-12-20T07:00:00Z","end":"2016-12-20T09:00:00Z"},{"uid":"ll-257","location":"","summary":"IZBRANI ALGORITMI, G2-P04, pritličje","description":" PR, MAG 1 RIT,  ","start":"2016-12-20T09:00:00Z","end":"2016-12-20T11:00:00Z"},{"uid":"ll-258","location":"","summary":"GENERATIVNE METODE, (RU) G-219","description":" RV, MAG 1 RIT RV 2,  ","start":"2016-12-20T11:00:00Z","end":"2016-12-20T13:00:00Z"},{"uid":"ll-259","location":"","summary":"RAČUNALNIŠKA MULTIMEDIA, (RU) F-104","description":" RV, MAG 1 RIT RV 1,  ","start":"2016-12-20T11:00:00Z","end":"2016-12-20T13:00:00Z"},{"uid":"ll-260","location":"","summary":"SPLETNE TEHNOLOGIJE, (RU) C-202","description":" RV, MAG 1 RIT RV 3,  ","start":"2016-12-21T08:00:00Z","end":"2016-12-21T10:00:00Z"},{"uid":"ll-261","location":"","summary":"PRINCIPI PROGRAMSKIH JEZIKOV, (RU) F-201","description":" RV, MAG 1 RIT RV 3,  ","start":"2016-12-21T10:00:00Z","end":"2016-12-21T12:00:00Z"},{"uid":"ll-262","location":"","summary":"SPLETNE TEHNOLOGIJE, (RU) C-202","description":" RV, MAG 1 RIT RV 2,  ","start":"2016-12-21T10:00:00Z","end":"2016-12-21T12:00:00Z"},{"uid":"ll-263","location":"","summary":"RAČUNALNIŠKA MULTIMEDIA, (RU) F-104","description":" RV, MAG 1 RIT RV 3,  ","start":"2016-12-21T12:00:00Z","end":"2016-12-21T14:00:00Z"},{"uid":"ll-264","location":"","summary":"RAČUNALNIŠKA MULTIMEDIA, (RU) F-104","description":" RV, MAG 1 RIT RV 2,  ","start":"2016-12-21T14:00:00Z","end":"2016-12-21T16:00:00Z"},{"uid":"ll-265","location":"","summary":"RAZVOJ IN UPRAVLJANJE PROGRAMSKIH SISTEMOV, (RU) G-219","description":" RV, MAG 1 RIT RV 3,  ","start":"2016-12-21T14:00:00Z","end":"2016-12-21T16:00:00Z"},{"uid":"ll-266","location":"","summary":"RAZVOJ IN UPRAVLJANJE PROGRAMSKIH SISTEMOV, (RU) C-202","description":" RV, MAG 1 RIT RV 2,  ","start":"2016-12-22T07:00:00Z","end":"2016-12-22T09:00:00Z"},{"uid":"ll-267","location":"","summary":"PRINCIPI PROGRAMSKIH JEZIKOV, (RU) F-201","description":" RV, MAG 1 RIT RV 1,  ","start":"2016-12-22T07:00:00Z","end":"2016-12-22T09:00:00Z"},{"uid":"ll-268","location":"","summary":"RAČUNALNIŠKA MULTIMEDIA, G2-P02, pritličje","description":" PR, MAG 1 RIT,  ","start":"2016-12-22T09:00:00Z","end":"2016-12-22T11:00:00Z"},{"uid":"ll-269","location":"","summary":"PRINCIPI PROGRAMSKIH JEZIKOV, (RU) C-202","description":" RV, MAG 1 RIT RV 2,  ","start":"2016-12-22T11:00:00Z","end":"2016-12-22T13:00:00Z"},{"uid":"ll-270","location":"","summary":"SPLETNE TEHNOLOGIJE, G2-P01, pritličje","description":" PR, MAG 1 RIT,  ","start":"2016-12-22T15:00:00Z","end":"2016-12-22T17:00:00Z"},{"uid":"ll-271","location":"","summary":"IZBRANI ALGORITMI, (RU) F-201","description":" RV, MAG 1 RIT RV 3,  ","start":"2016-12-22T17:00:00Z","end":"2016-12-22T19:00:00Z"},{"uid":"ll-272","location":"","summary":"SPLETNE TEHNOLOGIJE, (RU) C-202","description":" RV, MAG 1 RIT RV 1,  ","start":"2016-12-22T17:00:00Z","end":"2016-12-22T19:00:00Z"},{"uid":"ll-273","location":"","summary":"RAZVOJ IN UPRAVLJANJE PROGRAMSKIH SISTEMOV, (RU) C-202","description":" RV, MAG 1 RIT RV 1,  ","start":"2016-12-23T09:00:00Z","end":"2016-12-23T11:00:00Z"},{"uid":"ll-274","location":"","summary":"PRINCIPI PROGRAMSKIH JEZIKOV, A-302","description":" PR, MAG 1 RIT,  ","start":"2016-12-23T11:00:00Z","end":"2016-12-23T13:00:00Z"},{"uid":"ll-275","location":"","summary":"IZBRANI ALGORITMI, (RU) F-201","description":" RV, MAG 1 RIT RV 1,  ","start":"2016-12-23T13:00:00Z","end":"2016-12-23T15:00:00Z"},{"uid":"ll-276","location":"","summary":"IZBRANI ALGORITMI, (RU) F-201","description":" RV, MAG 1 RIT RV 2,  ","start":"2017-01-02T08:00:00Z","end":"2017-01-02T10:00:00Z"},{"uid":"ll-277","location":"","summary":"RAZVOJ IN UPRAVLJANJE PROGRAMSKIH SISTEMOV, G2-P4 DELTA, 2. nadstropje","description":" PR, MAG 1 RIT,  ","start":"2017-01-02T10:00:00Z","end":"2017-01-02T12:00:00Z"},{"uid":"ll-278","location":"","summary":"GENERATIVNE METODE, G2-P4 DELTA, 2. nadstropje","description":" PR, MAG 1 RIT,  ","start":"2017-01-02T12:00:00Z","end":"2017-01-02T14:00:00Z"},{"uid":"ll-279","location":"","summary":"GENERATIVNE METODE, (RU) G-219","description":" RV, MAG 1 RIT RV 3,  ","start":"2017-01-02T14:00:00Z","end":"2017-01-02T16:00:00Z"},{"uid":"ll-280","location":"","summary":"GENERATIVNE METODE, (RU) G-219","description":" RV, MAG 1 RIT RV 1,  ","start":"2017-01-03T07:00:00Z","end":"2017-01-03T09:00:00Z"},{"uid":"ll-281","location":"","summary":"IZBRANI ALGORITMI, G2-P04, pritličje","description":" PR, MAG 1 RIT,  ","start":"2017-01-03T09:00:00Z","end":"2017-01-03T11:00:00Z"},{"uid":"ll-282","location":"","summary":"RAČUNALNIŠKA MULTIMEDIA, (RU) F-104","description":" RV, MAG 1 RIT RV 1,  ","start":"2017-01-03T11:00:00Z","end":"2017-01-03T13:00:00Z"},{"uid":"ll-283","location":"","summary":"GENERATIVNE METODE, (RU) G-219","description":" RV, MAG 1 RIT RV 2,  ","start":"2017-01-03T11:00:00Z","end":"2017-01-03T13:00:00Z"},{"uid":"ll-284","location":"","summary":"SPLETNE TEHNOLOGIJE, (RU) C-202","description":" RV, MAG 1 RIT RV 3,  ","start":"2017-01-04T08:00:00Z","end":"2017-01-04T10:00:00Z"},{"uid":"ll-285","location":"","summary":"SPLETNE TEHNOLOGIJE, (RU) C-202","description":" RV, MAG 1 RIT RV 2,  ","start":"2017-01-04T10:00:00Z","end":"2017-01-04T12:00:00Z"},{"uid":"ll-286","location":"","summary":"PRINCIPI PROGRAMSKIH JEZIKOV, (RU) F-201","description":" RV, MAG 1 RIT RV 3,  ","start":"2017-01-04T10:00:00Z","end":"2017-01-04T12:00:00Z"},{"uid":"ll-287","location":"","summary":"RAČUNALNIŠKA MULTIMEDIA, (RU) F-104","description":" RV, MAG 1 RIT RV 3,  ","start":"2017-01-04T12:00:00Z","end":"2017-01-04T14:00:00Z"},{"uid":"ll-288","location":"","summary":"RAČUNALNIŠKA MULTIMEDIA, (RU) F-104","description":" RV, MAG 1 RIT RV 2,  ","start":"2017-01-04T14:00:00Z","end":"2017-01-04T16:00:00Z"},{"uid":"ll-289","location":"","summary":"RAZVOJ IN UPRAVLJANJE PROGRAMSKIH SISTEMOV, (RU) G-219","description":" RV, MAG 1 RIT RV 3,  ","start":"2017-01-04T14:00:00Z","end":"2017-01-04T16:00:00Z"},{"uid":"ll-290","location":"","summary":"RAZVOJ IN UPRAVLJANJE PROGRAMSKIH SISTEMOV, (RU) C-202","description":" RV, MAG 1 RIT RV 2,  ","start":"2017-01-05T07:00:00Z","end":"2017-01-05T09:00:00Z"},{"uid":"ll-291","location":"","summary":"PRINCIPI PROGRAMSKIH JEZIKOV, (RU) F-201","description":" RV, MAG 1 RIT RV 1,  ","start":"2017-01-05T07:00:00Z","end":"2017-01-05T09:00:00Z"},{"uid":"ll-292","location":"","summary":"RAČUNALNIŠKA MULTIMEDIA, G2-P02, pritličje","description":" PR, MAG 1 RIT,  ","start":"2017-01-05T09:00:00Z","end":"2017-01-05T11:00:00Z"},{"uid":"ll-293","location":"","summary":"PRINCIPI PROGRAMSKIH JEZIKOV, (RU) C-202","description":" RV, MAG 1 RIT RV 2,  ","start":"2017-01-05T11:00:00Z","end":"2017-01-05T13:00:00Z"},{"uid":"ll-294","location":"","summary":"SPLETNE TEHNOLOGIJE, G2-P01, pritličje","description":" PR, MAG 1 RIT,  ","start":"2017-01-05T15:00:00Z","end":"2017-01-05T17:00:00Z"},{"uid":"ll-295","location":"","summary":"IZBRANI ALGORITMI, (RU) F-201","description":" RV, MAG 1 RIT RV 3,  ","start":"2017-01-05T17:00:00Z","end":"2017-01-05T19:00:00Z"},{"uid":"ll-296","location":"","summary":"SPLETNE TEHNOLOGIJE, (RU) C-202","description":" RV, MAG 1 RIT RV 1,  ","start":"2017-01-05T17:00:00Z","end":"2017-01-05T19:00:00Z"},{"uid":"ll-297","location":"","summary":"RAZVOJ IN UPRAVLJANJE PROGRAMSKIH SISTEMOV, (RU) C-202","description":" RV, MAG 1 RIT RV 1,  ","start":"2017-01-06T09:00:00Z","end":"2017-01-06T11:00:00Z"},{"uid":"ll-298","location":"","summary":"PRINCIPI PROGRAMSKIH JEZIKOV, A-302","description":" PR, MAG 1 RIT,  ","start":"2017-01-06T11:00:00Z","end":"2017-01-06T13:00:00Z"},{"uid":"ll-299","location":"","summary":"IZBRANI ALGORITMI, (RU) F-201","description":" RV, MAG 1 RIT RV 1,  ","start":"2017-01-06T13:00:00Z","end":"2017-01-06T15:00:00Z"},{"uid":"ll-300","location":"","summary":"IZBRANI ALGORITMI, (RU) F-201","description":" RV, MAG 1 RIT RV 2,  ","start":"2017-01-09T08:00:00Z","end":"2017-01-09T10:00:00Z"},{"uid":"ll-301","location":"","summary":"RAZVOJ IN UPRAVLJANJE PROGRAMSKIH SISTEMOV, G2-P4 DELTA, 2. nadstropje","description":" PR, MAG 1 RIT,  ","start":"2017-01-09T10:00:00Z","end":"2017-01-09T12:00:00Z"},{"uid":"ll-302","location":"","summary":"GENERATIVNE METODE, G2-P4 DELTA, 2. nadstropje","description":" PR, MAG 1 RIT,  ","start":"2017-01-09T12:00:00Z","end":"2017-01-09T14:00:00Z"},{"uid":"ll-303","location":"","summary":"GENERATIVNE METODE, (RU) G-219","description":" RV, MAG 1 RIT RV 3,  ","start":"2017-01-09T14:00:00Z","end":"2017-01-09T16:00:00Z"},{"uid":"ll-304","location":"","summary":"GENERATIVNE METODE, (RU) G-219","description":" RV, MAG 1 RIT RV 1,  ","start":"2017-01-10T07:00:00Z","end":"2017-01-10T09:00:00Z"},{"uid":"ll-305","location":"","summary":"IZBRANI ALGORITMI, G2-P04, pritličje","description":" PR, MAG 1 RIT,  ","start":"2017-01-10T09:00:00Z","end":"2017-01-10T11:00:00Z"},{"uid":"ll-306","location":"","summary":"GENERATIVNE METODE, (RU) G-219","description":" RV, MAG 1 RIT RV 2,  ","start":"2017-01-10T11:00:00Z","end":"2017-01-10T13:00:00Z"},{"uid":"ll-307","location":"","summary":"RAČUNALNIŠKA MULTIMEDIA, (RU) F-104","description":" RV, MAG 1 RIT RV 1,  ","start":"2017-01-10T11:00:00Z","end":"2017-01-10T13:00:00Z"},{"uid":"ll-308","location":"","summary":"SPLETNE TEHNOLOGIJE, (RU) C-202","description":" RV, MAG 1 RIT RV 3,  ","start":"2017-01-11T08:00:00Z","end":"2017-01-11T10:00:00Z"},{"uid":"ll-309","location":"","summary":"SPLETNE TEHNOLOGIJE, (RU) C-202","description":" RV, MAG 1 RIT RV 2,  ","start":"2017-01-11T10:00:00Z","end":"2017-01-11T12:00:00Z"},{"uid":"ll-310","location":"","summary":"PRINCIPI PROGRAMSKIH JEZIKOV, (RU) F-201","description":" RV, MAG 1 RIT RV 3,  ","start":"2017-01-11T10:00:00Z","end":"2017-01-11T12:00:00Z"},{"uid":"ll-311","location":"","summary":"RAČUNALNIŠKA MULTIMEDIA, (RU) F-104","description":" RV, MAG 1 RIT RV 3,  ","start":"2017-01-11T12:00:00Z","end":"2017-01-11T14:00:00Z"},{"uid":"ll-312","location":"","summary":"RAČUNALNIŠKA MULTIMEDIA, (RU) F-104","description":" RV, MAG 1 RIT RV 2,  ","start":"2017-01-11T14:00:00Z","end":"2017-01-11T16:00:00Z"},{"uid":"ll-313","location":"","summary":"RAZVOJ IN UPRAVLJANJE PROGRAMSKIH SISTEMOV, (RU) G-219","description":" RV, MAG 1 RIT RV 3,  ","start":"2017-01-11T14:00:00Z","end":"2017-01-11T16:00:00Z"},{"uid":"ll-314","location":"","summary":"PRINCIPI PROGRAMSKIH JEZIKOV, (RU) F-201","description":" RV, MAG 1 RIT RV 1,  ","start":"2017-01-12T07:00:00Z","end":"2017-01-12T09:00:00Z"},{"uid":"ll-315","location":"","summary":"RAZVOJ IN UPRAVLJANJE PROGRAMSKIH SISTEMOV, (RU) C-202","description":" RV, MAG 1 RIT RV 2,  ","start":"2017-01-12T07:00:00Z","end":"2017-01-12T09:00:00Z"},{"uid":"ll-316","location":"","summary":"RAČUNALNIŠKA MULTIMEDIA, G2-P02, pritličje","description":" PR, MAG 1 RIT,  ","start":"2017-01-12T09:00:00Z","end":"2017-01-12T11:00:00Z"},{"uid":"ll-317","location":"","summary":"PRINCIPI PROGRAMSKIH JEZIKOV, (RU) C-202","description":" RV, MAG 1 RIT RV 2,  ","start":"2017-01-12T11:00:00Z","end":"2017-01-12T13:00:00Z"},{"uid":"ll-318","location":"","summary":"SPLETNE TEHNOLOGIJE, G2-P01, pritličje","description":" PR, MAG 1 RIT,  ","start":"2017-01-12T15:00:00Z","end":"2017-01-12T17:00:00Z"},{"uid":"ll-319","location":"","summary":"IZBRANI ALGORITMI, (RU) F-201","description":" RV, MAG 1 RIT RV 3,  ","start":"2017-01-12T17:00:00Z","end":"2017-01-12T19:00:00Z"},{"uid":"ll-320","location":"","summary":"SPLETNE TEHNOLOGIJE, (RU) C-202","description":" RV, MAG 1 RIT RV 1,  ","start":"2017-01-12T17:00:00Z","end":"2017-01-12T19:00:00Z"},{"uid":"ll-321","location":"","summary":"RAZVOJ IN UPRAVLJANJE PROGRAMSKIH SISTEMOV, (RU) C-202","description":" RV, MAG 1 RIT RV 1,  ","start":"2017-01-13T09:00:00Z","end":"2017-01-13T11:00:00Z"},{"uid":"ll-322","location":"","summary":"PRINCIPI PROGRAMSKIH JEZIKOV, A-302","description":" PR, MAG 1 RIT,  ","start":"2017-01-13T11:00:00Z","end":"2017-01-13T13:00:00Z"},{"uid":"ll-323","location":"","summary":"IZBRANI ALGORITMI, (RU) F-201","description":" RV, MAG 1 RIT RV 1,  ","start":"2017-01-13T13:00:00Z","end":"2017-01-13T15:00:00Z"},{"uid":"ll-324","location":"","summary":"IZBRANI ALGORITMI, (RU) F-201","description":" RV, MAG 1 RIT RV 2,  ","start":"2017-01-16T08:00:00Z","end":"2017-01-16T10:00:00Z"},{"uid":"ll-325","location":"","summary":"RAZVOJ IN UPRAVLJANJE PROGRAMSKIH SISTEMOV, G2-P4 DELTA, 2. nadstropje","description":" PR, MAG 1 RIT,  ","start":"2017-01-16T10:00:00Z","end":"2017-01-16T12:00:00Z"},{"uid":"ll-326","location":"","summary":"GENERATIVNE METODE, G2-P4 DELTA, 2. nadstropje","description":" PR, MAG 1 RIT,  ","start":"2017-01-16T12:00:00Z","end":"2017-01-16T14:00:00Z"},{"uid":"ll-327","location":"","summary":"GENERATIVNE METODE, (RU) G-219","description":" RV, MAG 1 RIT RV 3,  ","start":"2017-01-16T14:00:00Z","end":"2017-01-16T16:00:00Z"},{"uid":"ll-328","location":"","summary":"GENERATIVNE METODE, (RU) G-219","description":" RV, MAG 1 RIT RV 1,  ","start":"2017-01-17T07:00:00Z","end":"2017-01-17T09:00:00Z"},{"uid":"ll-329","location":"","summary":"IZBRANI ALGORITMI, G2-P04, pritličje","description":" PR, MAG 1 RIT,  ","start":"2017-01-17T09:00:00Z","end":"2017-01-17T11:00:00Z"},{"uid":"ll-330","location":"","summary":"GENERATIVNE METODE, (RU) G-219","description":" RV, MAG 1 RIT RV 2,  ","start":"2017-01-17T11:00:00Z","end":"2017-01-17T13:00:00Z"},{"uid":"ll-331","location":"","summary":"RAČUNALNIŠKA MULTIMEDIA, (RU) F-104","description":" RV, MAG 1 RIT RV 1,  ","start":"2017-01-17T11:00:00Z","end":"2017-01-17T13:00:00Z"},{"uid":"ll-332","location":"","summary":"SPLETNE TEHNOLOGIJE, (RU) C-202","description":" RV, MAG 1 RIT RV 3,  ","start":"2017-01-18T08:00:00Z","end":"2017-01-18T10:00:00Z"},{"uid":"ll-333","location":"","summary":"SPLETNE TEHNOLOGIJE, (RU) C-202","description":" RV, MAG 1 RIT RV 2,  ","start":"2017-01-18T10:00:00Z","end":"2017-01-18T12:00:00Z"},{"uid":"ll-334","location":"","summary":"PRINCIPI PROGRAMSKIH JEZIKOV, (RU) F-201","description":" RV, MAG 1 RIT RV 3,  ","start":"2017-01-18T10:00:00Z","end":"2017-01-18T12:00:00Z"},{"uid":"ll-335","location":"","summary":"RAČUNALNIŠKA MULTIMEDIA, (RU) F-104","description":" RV, MAG 1 RIT RV 3,  ","start":"2017-01-18T12:00:00Z","end":"2017-01-18T14:00:00Z"},{"uid":"ll-336","location":"","summary":"RAČUNALNIŠKA MULTIMEDIA, (RU) F-104","description":" RV, MAG 1 RIT RV 2,  ","start":"2017-01-18T14:00:00Z","end":"2017-01-18T16:00:00Z"},{"uid":"ll-337","location":"","summary":"RAZVOJ IN UPRAVLJANJE PROGRAMSKIH SISTEMOV, (RU) G-219","description":" RV, MAG 1 RIT RV 3,  ","start":"2017-01-18T14:00:00Z","end":"2017-01-18T16:00:00Z"},{"uid":"ll-338","location":"","summary":"PRINCIPI PROGRAMSKIH JEZIKOV, (RU) F-201","description":" RV, MAG 1 RIT RV 1,  ","start":"2017-01-19T07:00:00Z","end":"2017-01-19T09:00:00Z"},{"uid":"ll-339","location":"","summary":"RAZVOJ IN UPRAVLJANJE PROGRAMSKIH SISTEMOV, (RU) C-202","description":" RV, MAG 1 RIT RV 2,  ","start":"2017-01-19T07:00:00Z","end":"2017-01-19T09:00:00Z"},{"uid":"ll-340","location":"","summary":"RAČUNALNIŠKA MULTIMEDIA, G2-P02, pritličje","description":" PR, MAG 1 RIT,  ","start":"2017-01-19T09:00:00Z","end":"2017-01-19T11:00:00Z"},{"uid":"ll-341","location":"","summary":"PRINCIPI PROGRAMSKIH JEZIKOV, (RU) C-202","description":" RV, MAG 1 RIT RV 2,  ","start":"2017-01-19T11:00:00Z","end":"2017-01-19T13:00:00Z"},{"uid":"ll-342","location":"","summary":"SPLETNE TEHNOLOGIJE, G2-P01, pritličje","description":" PR, MAG 1 RIT,  ","start":"2017-01-19T15:00:00Z","end":"2017-01-19T17:00:00Z"},{"uid":"ll-343","location":"","summary":"IZBRANI ALGORITMI, (RU) F-201","description":" RV, MAG 1 RIT RV 3,  ","start":"2017-01-19T17:00:00Z","end":"2017-01-19T19:00:00Z"},{"uid":"ll-344","location":"","summary":"SPLETNE TEHNOLOGIJE, (RU) C-202","description":" RV, MAG 1 RIT RV 1,  ","start":"2017-01-19T17:00:00Z","end":"2017-01-19T19:00:00Z"},{"uid":"ll-345","location":"","summary":"RAZVOJ IN UPRAVLJANJE PROGRAMSKIH SISTEMOV, (RU) C-202","description":" RV, MAG 1 RIT RV 1,  ","start":"2017-01-20T09:00:00Z","end":"2017-01-20T11:00:00Z"},{"uid":"ll-346","location":"","summary":"PRINCIPI PROGRAMSKIH JEZIKOV, A-302","description":" PR, MAG 1 RIT,  ","start":"2017-01-20T11:00:00Z","end":"2017-01-20T13:00:00Z"},{"uid":"ll-347","location":"","summary":"IZBRANI ALGORITMI, (RU) F-201","description":" RV, MAG 1 RIT RV 1,  ","start":"2017-01-20T13:00:00Z","end":"2017-01-20T15:00:00Z"}]}
